{"article_article_1.md":"fcada2b1","article_milepost_2022.md":"0de4fd5d","article_article_11.md":"d8eee73b","article_milepost_2024.md":"e72fb0d1","article_article_3.md":"dedbab2d","article_article_4.md":"e4f0177a","article_article_5.md":"16941187","article_article_6.md":"d514b297","article_vue-design_4.md":"46de1201","article_article_7.md":"74f2d499","article_article_8.md":"52bc3d12","article_design-mode_1.md":"27c5bc50","article_design-mode_11.md":"c47fe018","article_article_9.md":"7c4c2b42","article_design-mode_10.md":"99099659","article_design-mode_14.md":"f56a9b87","article_design-mode_13.md":"68c57bf1","article_article_17.md":"2221b825","article_article_14.md":"5cac1a5d","article_article_21.md":"cc948b97","article_design-mode_8.md":"0f1760b4","article_design-mode_4.md":"c7643aea","readme.md":"b4e4b73c","article_design-mode_9.md":"085d946d","docs_javascript_10.md":"f84a83ef","docs_hello_hello.md":"4ee9cdd0","article_annual-summary_2022.md":"583a78de","docs_hello_lol.md":"4e0f83e0","article_milepost_2021.md":"586b46b8","article_ques_3.md":"c9629f81","docs_javascript_1.md":"353d615d","article_ques_6.md":"288245ed","article_ques_2.md":"05a25fc8","article_vue-design_2.md":"3d79e00e","article_ques_1.md":"7fe5ffb0","article_article_16.md":"f7c7894e","article_article_15.md":"6db03c13","article_design-mode_3.md":"f620b084","article_article_18.md":"f9ef5c00","article_design-mode_2.md":"e9da328c","article_annual-summary_2023.md":"4ec19199","article_design-mode_5.md":"ff0fe633","article_vue-design_5.md":"0a063e71","article_article_13.md":"3bd91e8d","article_article_12.md":"e33e688d","article_vue-design_1.md":"252c59b5","article_design-mode_7.md":"52c9bb55","article_design-mode_6.md":"3dfd2ae7","article_article_2.md":"62c01f13","article_article_19.md":"2f9dbba5","article_ques_5.md":"e4aaac00","article_article_10.md":"f777f8f0","docs_javascript_5.md":"6279c8f5","docs_nest_1.md":"3dafb0ef","docs_react_3.md":"a7ed5551","docs_javascript_6.md":"85579faf","docs_javascript_11.md":"ee419c0f","docs_server_3.md":"2ad2fa89","docs_react_4.md":"23500954","docs_server_1.md":"af26979f","docs_node_1.md":"7661477b","docs_swift_1.md":"75abec67","docs_server_4.md":"dcf7eb7b","docs_server_2.md":"9bceac58","docs_react_6.md":"4793860c","docs_react_5.md":"deaad4e3","docs_system_2.md":"4e14f114","docs_system_3.md":"224f24f1","docs_typescript_2.md":"cfdeecb5","docs_typescript_1.md":"d298ca79","docs_javascript_14.md":"059b1972","docs_vue_3.md":"eba45169","docs_javascript_15.md":"00859072","docs_javascript_17.md":"3a7ad2b0","index.md":"f9a1a2e3","docs_vue_1.md":"7a5b03af","docs_vue_5.md":"127a329a","docs_javascript_4.md":"6d0d972c","docs_vue_4.md":"a45b046a","docs_javascript_16.md":"5978a8ef","docs_javascript_12.md":"2e2446ca","docs_javascript_7.md":"e15572b8","article_vue-design_3.md":"3e974ea0","docs_vue_2.md":"d0b6e285","article_design-mode_12.md":"452cf5ec","article_article_20.md":"cac9584e","docs_react_1.md":"12064287","docs_swift_2.md":"2c0342a6","docs_system_1.md":"d6f7dbd0","article_ques_4.md":"af8b7d9c","docs_javascript_9.md":"d4a268b0","docs_react_2.md":"cecbddbc","docs_javascript_3.md":"79c93a6d","docs_javascript_8.md":"e55f42ff","docs_javascript_13.md":"dfa53a67","docs_javascript_2.md":"579ce062"}
