{"article_annual-summary_2022.md":"hMdy4xD0","article_article_10.md":"Bp4zLYhr","article_article_11.md":"Ddd3C880","article_article_4.md":"uPVZNTjC","article_article_12.md":"D2560IIh","article_article_13.md":"ClRkzP2z","article_article_17.md":"CLq4u7pK","article_design-mode_2.md":"DC1Ez438","article_vue-design_4.md":"BY3FYuEC","article_article_1.md":"9nUcn-m2","article_article_5.md":"BTp5kjrU","article_article_22.md":"6P_33vH_","docs_react_3.md":"DaG18JHp","article_article_2.md":"Bux3UV7w","article_article_15.md":"BwhFKPXz","docs_server_2.md":"mwYU12qc","docs_server_3.md":"BPJWNvHL","docs_server_4.md":"jAxWu-CV","article_design-mode_7.md":"BXGhx_tB","docs_swift_1.md":"Bji9SHv3","docs_swift_11.md":"B3KfIQox","article_article_16.md":"CTkFjf6m","docs_swift_12.md":"-VOnzSAN","docs_swift_17.md":"5p3YzM-k","article_design-mode_13.md":"B9moOA1f","docs_swift_2.md":"Bb4PHbVD","article_design-mode_1.md":"DWUljymj","docs_react_5.md":"rq7_kPU1","article_article_3.md":"OLXt6PiQ","article_article_19.md":"BXsE92rZ","article_design-mode_10.md":"DNAhOKsp","article_article_20.md":"D36aEMj_","docs_swift_13.md":"CH3bP8UR","readme.md":"IWeTRCAQ","docs_server_1.md":"CyHqrI4i","article_article_18.md":"CC8Wdtal","article_article_14.md":"DMSP4JyO","article_design-mode_5.md":"DbApYyLr","article_design-mode_14.md":"C674PIYb","docs_javascript_6.md":"SaWtYxLL","article_milestone_2024.md":"ah97kNQg","article_design-mode_3.md":"C_i6EiIt","article_ques_3.md":"C_zqn0DV","docs_react_6.md":"J1o1oLBC","article_design-mode_4.md":"DlYlgVoC","docs_react_4.md":"DdYwnLtq","docs_node_1.md":"B7mmQ7x7","article_article_7.md":"BGH_iOKL","article_design-mode_11.md":"CHxI7i6n","docs_javascript_11.md":"B2Ma-98o","docs_javascript_13.md":"CZv-pevQ","docs_swift_10.md":"DtivRDWu","article_annual-summary_2023.md":"D1dX63RA","docs_javascript_2.md":"Dyl5arrZ","docs_javascript_15.md":"B-MdO9sw","docs_javascript_16.md":"gFD075yI","docs_javascript_12.md":"BKQph3lL","docs_javascript_5.md":"CEnWyPHp","article_vue-design_5.md":"C1HhFyBn","article_vue-design_1.md":"Bsl1fnoY","docs_hello_hello.md":"D2nhXDaf","docs_hello_lol.md":"BoHHGY1i","article_milestone_2022.md":"MA7u-Q9y","article_design-mode_12.md":"O0QfW18d","article_ques_1.md":"CLQoqS2o","docs_swift_16.md":"D0nFsd4L","docs_javascript_4.md":"vs3Sgzu8","docs_swift_15.md":"ZURSpUVZ","docs_swift_14.md":"DgobWs8H","article_article_21.md":"CorC71Bv","docs_javascript_17.md":"BVFZpu4u","article_article_9.md":"DXZOCCh4","article_article_6.md":"sLbFS4No","docs_javascript_8.md":"BlaWQvGH","docs_javascript_14.md":"C2V-y-3I","article_design-mode_6.md":"lD2ZMtYv","docs_javascript_7.md":"DwQbF6aS","docs_nest_1.md":"CGCxl9Hz","docs_swift_3.md":"CiszFIpQ","docs_swift_4.md":"Hu_NTaGA","docs_swift_5.md":"BnDZdIbA","docs_swift_6.md":"BOazMPLc","docs_react_1.md":"D1881OSY","docs_swift_7.md":"DHvZ9b9G","docs_swift_8.md":"CLor_pUC","docs_system_1.md":"BdpeUKhl","docs_system_2.md":"Faa_aBBC","docs_swift_9.md":"tPawn-yg","docs_vue_5.md":"ETCcN-rM","index.md":"DpJA74QY","docs_vue_4.md":"BI1QmkIt","article_ques_5.md":"B7cJcPSJ","article_ques_2.md":"DeNs6SCV","article_vue-design_3.md":"ix-UQVft","article_ques_6.md":"Lc5ngduv","article_vue-design_2.md":"CL01jNnl","docs_javascript_10.md":"D2vII-Gm","article_article_8.md":"fs9El7KH","article_ques_4.md":"DE7fcfOB","docs_system_3.md":"cnYKwL6J","docs_vue_3.md":"h77R0IaR","docs_typescript_1.md":"i4PfVOBP","docs_typescript_2.md":"_FNd3cl4","docs_javascript_3.md":"DiIgtT85","docs_javascript_1.md":"BfYcGGKY","article_design-mode_8.md":"CvGZYMSV","docs_vue_1.md":"CkPDIJ2y","article_design-mode_9.md":"BxEpjKGQ","docs_javascript_9.md":"CQh055-w","article_milestone_2021.md":"JZiAevXH","docs_react_2.md":"Bfbculzg","docs_vue_2.md":"Conz9f-1"}
